<?xml version="1.0" encoding="UTF-8"?><zahtev_za_autorska_prava><podaci_o_zavodu><naziv>Zavod za intelektualnu svojinu</naziv><adresa><ulica>Kneginja Ljubice 5</ulica><mesto>Beograd</mesto></adresa></podaci_o_zavodu><podaci_o_zahtevu><datum_podnosenja>19/08/2023</datum_podnosenja><obrazac>A-1</obrazac></podaci_o_zahtevu><podaci_o_podnosiocu><licni_podaci tip_lica="pravno"><ime>JKLJL</ime><adresa><ulica>LKJ</ulica><mesto>LKJ</mesto></adresa></licni_podaci><telefon>809</telefon><email>JH</email><pseudonim>IJ</pseudonim></podaci_o_podnosiocu><podaci_punomocnika><ime>JIO</ime><prezime>JIO</prezime><adresa><ulica>JIO</ulica><mesto>JIO</mesto></adresa></podaci_punomocnika><podaci_o_autorskom_delu><naslov>IOJ</naslov><alternativni_naslov>IOJ</alternativni_naslov><podaci_o_izvornom_delu><naslov>IJO</naslov><autor>IJO</autor></podaci_o_izvornom_delu><vrsta_autorskog_dela>Muzicko</vrsta_autorskog_dela><forma_autorskog_dela>Stampani tekst</forma_autorskog_dela><stvoreno_u_radnom_odnosu>false</stvoreno_u_radnom_odnosu><nacin_koriscenja>PIO</nacin_koriscenja></podaci_o_autorskom_delu><podaci_o_autoru_ziv><ime>PIO</ime><prezime>PIO</prezime><adresa><ulica>PPO</ulica><mesto>PIO</mesto></adresa><drzavljanstvo>PIO</drzavljanstvo><pseudonim>POI</pseudonim></podaci_o_autoru_ziv><prilozi><opis_autorskog_dela>true</opis_autorskog_dela><primer_autorskog_dela>true</primer_autorskog_dela></prilozi></zahtev_za_autorska_prava>